pyforms/__init__.py
pyforms/basewidget.py
pyforms/controls.py
pyforms/dialogs.py
pyforms/settings.py
PyForms-4.0.3.dist-info/LICENSE
PyForms-4.0.3.dist-info/METADATA
PyForms-4.0.3.dist-info/WHEEL
PyForms-4.0.3.dist-info/top_level.txt
PyForms-4.0.3.dist-info/RECORD
