Metadata-Version: 2.1
Name: PyForms
Version: 4.0.3
Summary: Pyforms is a Python framework to develop GUI applications based on pyqt
Home-page: https://github.com/UmSenhorQualquer/pyforms
Author: Ricardo Ribeiro
Author-email: ricardojvr@gmail.com
License: MIT
Platform: UNKNOWN
Requires-Dist: pyforms-terminal
Requires-Dist: pyforms-gui
Requires-Dist: pyforms-web
